dmarcmsg/__init__.py
dmarcmsg/construct.py
dmarcmsg/__pycache__/__init__.cpython-37.pyc
dmarcmsg/__pycache__/construct.cpython-37.pyc
dmarcmsg/util/__init__.py
dmarcmsg/util/content_disposition.py
dmarcmsg-0.3.0.dist-info/LICENSE
dmarcmsg-0.3.0.dist-info/METADATA
dmarcmsg-0.3.0.dist-info/WHEEL
dmarcmsg-0.3.0.dist-info/top_level.txt
dmarcmsg-0.3.0.dist-info/RECORD
