Metadata-Version: 2.1
Name: dmarcmsg
Version: 0.3.0
Summary: DMARC-Compliant Message Constructor Library for List-Servs.
Home-page: https://gitlab.com/teward/dmarcmsg
Author: Thomas Ward
Author-email: teward@dark-net.io
License: AGPLv3+
Download-URL: https://pypi.python.org/pypi/dmarcmsg
Keywords: email dmarc listserv
Platform: any
Classifier: Development Status :: 4 - Beta
Classifier: Environment :: Console
Classifier: Environment :: Other Environment
Classifier: Intended Audience :: Developers
Classifier: License :: OSI Approved :: GNU Affero General Public License v3 or later (AGPLv3+)
Classifier: Operating System :: OS Independent
Classifier: Programming Language :: Python
Classifier: Programming Language :: Python :: 3
Classifier: Programming Language :: Python :: 3.5
Classifier: Programming Language :: Python :: 3.6
Classifier: Programming Language :: Python :: 3.7
Classifier: Topic :: Communications :: Email
Classifier: Topic :: Software Development :: Libraries :: Python Modules
Requires-Python: >=3.5
